custom_file_organizer/__init__.py
custom_file_organizer/core.py
custom_file_organizer-0.1.0.dist-info/METADATA
custom_file_organizer-0.1.0.dist-info/WHEEL
custom_file_organizer-0.1.0.dist-info/top_level.txt
custom_file_organizer-0.1.0.dist-info/RECORD
