Metadata-Version: 2.4
Name: custom_file_organizer
Version: 0.1.0
Summary: A Python package to organize folders by file type automatically with user customization
Home-page: https://github.com/Sreeharish-0605/OrganizeFolder
Author: Sree Harish T
Author-email: sreeharish0605@gmail.com
License: MIT
Classifier: Programming Language :: Python :: 3
Classifier: License :: OSI Approved :: MIT License
Classifier: Operating System :: OS Independent
Requires-Python: >=3.6
